scvi_colab/__init__.py
scvi_colab/_core.py
scvi_colab-0.13.0.dist-info/LICENSE
scvi_colab-0.13.0.dist-info/METADATA
scvi_colab-0.13.0.dist-info/WHEEL
scvi_colab-0.13.0.dist-info/RECORD
